Workbook

Sheet Summary
A1: Company P&L 2025 — Executive Summary
A2: FY 2025 · All amounts in Turkish Lira (₺)
A3: ⚠ SYNTHETIC / DUMMY DATA — generated to demonstrate FP&A methodology. No real company figures.
A5: Headline KPIs
A6: Total Revenue | B6: ='P&L Statement'!N10 -> 1.341223e+08
A7: Total Expenses | B7: ='P&L Statement'!N40 -> 1.1499033e+08
A8: Net Profit | B8: ='P&L Statement'!N41 -> 19131972
A9: Contribution Margin | B9: ='P&L Statement'!N26 -> 65698226
A10: Net Margin % | B10: =IF('P&L Statement'!N10=0,0,'P&L Statement'!N41/'P&L Statement'!N10) -> 0.14264571
A11: Cost Ratio | B11: =IF('P&L Statement'!N10=0,0,'P&L Statement'!N40/'P&L Statement'!N10) -> 0.85735429
A12: Variable Cost Ratio | B12: =IF('P&L Statement'!N10=0,0,'P&L Statement'!N24/'P&L Statement'!N10) -> 0.51016181
A13: Fixed Cost Ratio | B13: =IF('P&L Statement'!N10=0,0,'P&L Statement'!N38/'P&L Statement'!N10) -> 0.34719247
A14: Loss Months (count) | B14: =COUNTIF('P&L Statement'!B41:M41,"<0") -> 2
A17: Quarterly Breakdown
A18: Quarter | B18: Revenue (₺) | C18: Expenses (₺) | D18: Net (₺) | E18: Net Margin %
A19: Q1 | B19: =SUM('P&L Statement'!B10:D10) -> 34157932 | C19: =SUM('P&L Statement'!B40:D40) -> 29505432 | D19: =SUM('P&L Statement'!B41:D41) -> 4652499.8 | E19: =IF(B19=0,0,D19/B19) -> 0.13620555
A20: Q2 | B20: =SUM('P&L Statement'!E10:G10) -> 32113828 | C20: =SUM('P&L Statement'!E40:G40) -> 27848187 | D20: =SUM('P&L Statement'!E41:G41) -> 4265641.2 | E20: =IF(B20=0,0,D20/B20) -> 0.1328288
A21: Q3 | B21: =SUM('P&L Statement'!H10:J10) -> 32041974 | C21: =SUM('P&L Statement'!H40:J40) -> 30128306 | D21: =SUM('P&L Statement'!H41:J41) -> 1913667.9 | E21: =IF(B21=0,0,D21/B21) -> 0.059723783
A22: Q4 | B22: =SUM('P&L Statement'!K10:M10) -> 35808571 | C22: =SUM('P&L Statement'!K40:M40) -> 27508408 | D22: =SUM('P&L Statement'!K41:M41) -> 8300162.7 | E22: =IF(B22=0,0,D22/B22) -> 0.23179263
A23: FY 2025 | B23: =SUM(B19:B22) -> 1.341223e+08 | C23: =SUM(C19:C22) -> 1.1499033e+08 | D23: =SUM(D19:D22) -> 19131972 | E23: =IF(B23=0,0,D23/B23) -> 0.14264571
A26: Legend
A27: Blue text = hardcoded monthly input · Black = in-sheet formula · Green = link to another tab
A28: Edit only the blue input cells on the P&L Statement tab; every total and ratio recalculates.

Sheet P&L Statement
A1: Company P&L Statement — FY 2025
A2: Full-year Profit & Loss by month · All amounts in Turkish Lira (₺) · SYNTHETIC / DUMMY DATA
A4: Line Item | B4: Jan | C4: Feb | D4: Mar | E4: Apr | F4: May | G4: Jun | H4: Jul | I4: Aug | J4: Sep | K4: Oct | L4: Nov | M4: Dec | N4: FY 2025
A5: REVENUE
A6: Domestic Sales | B6: 5301875.8 | C6: 5262257.5 | D6: 5346940.7 | E6: 6465227.6 | F6: 5324566.1 | G6: 3441139.1 | H6: 5956937.7 | I6: 5132411 | J6: 5201681.8 | K6: 5659341.6 | L6: 5819409.4 | M6: 7099893.2 | N6: =SUM(B6:M6) -> 66011681
A7: Export Sales | B7: 1396990.9 | C7: 1233152.1 | D7: 978503.52 | E7: 895601.29 | F7: 1273902.7 | G7: 1593324.2 | H7: 1212497.1 | I7: 1168103 | J7: 1359532.9 | K7: 763936.41 | L7: 1106316.8 | M7: 1347108.8 | N7: =SUM(B7:M7) -> 14328970
A8: Product A Sales | B8: 3411383.1 | C8: 2631559.2 | D8: 3063619.9 | E8: 2973749.4 | F8: 3347628.8 | G8: 2020744.4 | H8: 3197775.5 | I8: 1739835.7 | J8: 966038.2 | K8: 2375176.5 | L8: 2158933 | M8: 3413208.6 | N8: =SUM(B8:M8) -> 31299652
A9: Product B Sales | B9: 2098919.6 | C9: 1251416.4 | D9: 2181312.6 | E9: 1349008.7 | F9: 1761190.3 | G9: 1667745.1 | H9: 1851488.9 | I9: 2168386.3 | J9: 2087286.2 | K9: 1957448.3 | L9: 2092476.6 | M9: 2015321.4 | N9: =SUM(B9:M9) -> 22482001
A10: Total Revenue | B10: =SUM(B6:B9) -> 12209169 | C10: =SUM(C6:C9) -> 10378385 | D10: =SUM(D6:D9) -> 11570377 | E10: =SUM(E6:E9) -> 11683587 | F10: =SUM(F6:F9) -> 11707288 | G10: =SUM(G6:G9) -> 8722952.9 | H10: =SUM(H6:H9) -> 12218699 | I10: =SUM(I6:I9) -> 10208736 | ... M10: =SUM(M6:M9) -> 13875532 | N10: =SUM(B10:M10) -> 1.341223e+08
A12: VARIABLE COSTS
A13: General Production Costs | B13: 304523.89 | C13: 883305.79 | D13: 854222.33 | E13: 646888.82 | F13: 632365.43 | G13: 749566.79 | H13: 1073414.3 | I13: 552168.62 | J13: 669786.56 | K13: 1005334.6 | L13: 666346.73 | M13: 681702.85 | N13: =SUM(B13:M13) -> 8719626.8
A14: Raw Material A | B14: 1085269 | C14: 781194.5 | D14: 515408.21 | E14: 693584.69 | F14: 990579.15 | G14: 511264.32 | H14: 806706.26 | I14: 850647.47 | J14: 736881.57 | K14: 944726.4 | L14: 916155.95 | M14: 1264281.7 | N14: =SUM(B14:M14) -> 10096699
A15: Raw Material B | B15: 692995.17 | C15: 508589.48 | D15: 515730.36 | E15: 475262.83 | F15: 742841.03 | G15: 514975.07 | H15: 589460.88 | I15: 712395.39 | J15: 491480.55 | K15: 555951.31 | L15: 323807.06 | M15: 437628.21 | N15: =SUM(B15:M15) -> 6561117.3
A16: Subcontractor Payments | B16: 512222.04 | C16: 344838.83 | D16: 527493.18 | E16: 348797.8 | F16: 610649.79 | G16: 500397.6 | H16: 785428.93 | I16: 535105.06 | J16: 670711.19 | K16: 337092 | L16: 484732.58 | M16: 540393.21 | N16: =SUM(B16:M16) -> 6197862.2
A17: Trade Goods X | B17: 343226.36 | C17: 441576.1 | D17: 519349.33 | E17: 398153.32 | F17: 426136.43 | G17: 416796.94 | H17: 508474.11 | I17: 489335.52 | J17: 427369.33 | K17: 298905.57 | L17: 490338.53 | M17: 438104.71 | N17: =SUM(B17:M17) -> 5197766.2
A18: Trade Goods Y | B18: 457357.39 | C18: 347383.17 | D18: 520896.33 | E18: 318598.32 | F18: 489392.79 | G18: 360072.91 | H18: 304826.46 | I18: 251260.81 | J18: 336784.83 | K18: 474540.59 | L18: 421432.77 | M18: 410277.34 | N18: =SUM(B18:M18) -> 4692823.7
A19: Operating (COGS) subtotal | B19: =SUM(B13:B18) -> 3395593.9 | C19: =SUM(C13:C18) -> 3306887.9 | D19: =SUM(D13:D18) -> 3453099.7 | E19: =SUM(E13:E18) -> 2881285.8 | F19: =SUM(F13:F18) -> 3891964.6 | G19: =SUM(G13:G18) -> 3053073.6 | H19: =SUM(H13:H18) -> 4068310.9 | I19: =SUM(I13:I18) -> 3390912.9 | ... M19: =SUM(M13:M18) -> 3772388 | N19: =SUM(B19:M19) -> 41465895
A20: Marketing & Distribution (semi-variable) | B20: 287286.05 | C20: 115954.2 | D20: 249530.98 | E20: 229567.7 | F20: 276677.31 | G20: 235619.28 | H20: 202603.56 | I20: 173917.52 | J20: 137591.01 | K20: 209771.14 | L20: 190415.16 | M20: 301013.37 | N20: =SUM(B20:M20) -> 2609947.3
A21: FX Losses | B21: 92076.28 | C21: 51042.39 | D21: 33580.44 | E21: 40302.44 | F21: 75631.1 | G21: 75013.34 | H21: 83645.47 | I21: 62183.76 | J21: 53433.42 | K21: 38056.38 | L21: 83336.86 | M21: 84123.54 | N21: =SUM(B21:M21) -> 772425.42
A22: Other Ordinary Losses | B22: 8737.74 | C22: 8383.89 | D22: 6666.25 | E22: 9361.21 | F22: 6761.36 | G22: 5843.54 | H22: 6088.99 | I22: 5976.58 | J22: 3209.96 | K22: 7273.57 | L22: 7437.3 | M22: 6366.03 | N22: =SUM(B22:M22) -> 82106.42
A23: Short-Term Borrowing Costs | B23: 2097572.9 | C23: 1884707.1 | D23: 3078712.9 | E23: 1666416.6 | F23: 1940546.9 | G23: 1809188.4 | H23: 1586808 | I23: 2652792 | J23: 2312774 | K23: 1092218.6 | L23: 1512064.5 | M23: 1859901.4 | N23: =SUM(B23:M23) -> 23493703
A24: Total Variable Costs | B24: =SUM(B13:B23)-B19 -> 5881266.8 | C24: =SUM(C13:C23)-C19 -> 5366975.5 | D24: =SUM(D13:D23)-D19 -> 6821590.3 | E24: =SUM(E13:E23)-E19 -> 4826933.8 | F24: =SUM(F13:F23)-F19 -> 6191581.2 | G24: =SUM(G13:G23)-G19 -> 5178738.2 | H24: =SUM(H13:H23)-H19 -> 5947457 | I24: =SUM(I13:I23)-I19 -> 6285782.7 | ... M24: =SUM(M13:M23)-M19 -> 6023792.3 | N24: =SUM(B24:M24) -> 68424078
A26: CONTRIBUTION MARGIN | B26: =B10-B24 -> 6327902.7 | C26: =C10-C24 -> 5011409.8 | D26: =D10-D24 -> 4748786.4 | E26: =E10-E24 -> 6856653.3 | F26: =F10-F24 -> 5515706.6 | G26: =G10-G24 -> 3544214.6 | H26: =H10-H24 -> 6271242.2 | I26: =I10-I24 -> 3922953.4 | ... M26: =M10-M24 -> 7851739.6 | N26: =SUM(B26:M26) -> 65698226
A28: FIXED COSTS
A29: Salary & Social Security | B29: 1355590.1 | C29: 1728156.7 | D29: 972399.43 | E29: 1441815 | F29: 1704459.1 | G29: 1929584 | H29: 2179240.7 | I29: 1582340.7 | J29: 1153102.1 | K29: 1783140.2 | L29: 1806794.8 | M29: 1796663.3 | N29: =SUM(B29:M29) -> 19433286
A30: Loan Installments | B30: 1417019.1 | C30: 1608218.9 | D30: 1197442.7 | E30: 1131191.9 | F30: 724446.01 | G30: 828648.75 | H30: 1062315.4 | I30: 1182089.4 | J30: 1202298.4 | K30: 924470.25 | L30: 747615.17 | M30: 845832.27 | N30: =SUM(B30:M30) -> 12871588
A31: Financing Costs | B31: 262993.52 | C31: 362616.5 | D31: 469611.28 | E31: 492800.7 | F31: 555488.5 | G31: 393013.7 | H31: 251763.67 | I31: 374321.87 | J31: 550223.38 | K31: 468894.58 | L31: 214521.43 | M31: 416319.59 | N31: =SUM(B31:M31) -> 4812568.7
A32: Credit Card Payments | B32: 227442.05 | C32: 371472.73 | D32: 135017.51 | E32: 293337.76 | F32: 355990.27 | G32: 441761.02 | H32: 325703.97 | I32: 400102.72 | J32: 288079.67 | K32: 260447.68 | L32: 266048.56 | M32: 442186.86 | N32: =SUM(B32:M32) -> 3807590.8
A33: General & Admin Costs | B33: 132372.48 | C33: 162499.33 | D33: 148697.14 | E33: 168099.66 | F33: 75798.89 | G33: 240098.71 | H33: 153320.12 | I33: 229716.22 | J33: 119715.51 | K33: 171701.43 | L33: 286597.68 | M33: 125210.83 | N33: =SUM(B33:M33) -> 2013828
A34: Overtime | B34: 82492.81 | C34: 128334.61 | D34: 102197.4 | E34: 117495.62 | F34: 131851.83 | G34: 115231.81 | H34: 107162.9 | I34: 153819.88 | J34: 106092.58 | K34: 92600.89 | L34: 102799.18 | M34: 137069.22 | N34: =SUM(B34:M34) -> 1377148.7
A35: Vehicle Insurance & Tax | B35: 80055.12 | C35: 125320.21 | D35: 42753.94 | E35: 93905.68 | F35: 73875.1 | G35: 77996.05 | H35: 118031.78 | I35: 79828.54 | J35: 124818.87 | K35: 71157.04 | L35: 87010.24 | M35: 70183.05 | N35: =SUM(B35:M35) -> 1044935.6
A36: Bonus Expense | B36: 72077.47 | C36: 79089.11 | D36: 90925.3 | E36: 61024.97 | F36: 39785.03 | G36: 75239.91 | H36: 74020.36 | I36: 59359.82 | J36: 85244.01 | K36: 80632.43 | L36: 52587.63 | M36: 79068.82 | N36: =SUM(B36:M36) -> 849054.86
A37: Water Expense | B37: 28529.21 | C37: 18877.31 | D37: 33397.13 | E37: 29660.89 | F37: 24410.38 | G37: 33922.09 | H37: 33660.7 | I37: 25668.47 | J37: 33002.64 | K37: 37612.99 | L37: 24655 | M37: 32856.68 | N37: =SUM(B37:M37) -> 356253.49
A38: Total Fixed Costs | B38: =SUM(B29:B37) -> 3658571.9 | C38: =SUM(C29:C37) -> 4584585.4 | D38: =SUM(D29:D37) -> 3192441.9 | E38: =SUM(E29:E37) -> 3829332.1 | F38: =SUM(F29:F37) -> 3686105.2 | G38: =SUM(G29:G37) -> 4135496 | H38: =SUM(H29:H37) -> 4305219.6 | I38: =SUM(I29:I37) -> 4087247.7 | ... M38: =SUM(M29:M37) -> 3945390.7 | N38: =SUM(B38:M38) -> 46566255
A40: Total Operating Expenses | B40: =B24+B38 -> 9539838.7 | C40: =C24+C38 -> 9951560.9 | D40: =D24+D38 -> 10014032 | E40: =E24+E38 -> 8656265.9 | F40: =F24+F38 -> 9877686.4 | G40: =G24+G38 -> 9314234.3 | H40: =H24+H38 -> 10252677 | I40: =I24+I38 -> 10373030 | ... M40: =M24+M38 -> 9969183 | N40: =SUM(B40:M40) -> 1.1499033e+08
A41: NET PROFIT / (LOSS) | B41: =B10-B40 -> 2669330.8 | C41: =C10-C40 -> 426824.39 | D41: =D10-D40 -> 1556344.6 | E41: =E10-E40 -> 3027321.2 | F41: =F10-F40 -> 1829601.4 | G41: =G10-G40 -> -591281.43 | H41: =H10-H40 -> 1966022.6 | I41: =I10-I40 -> -164294.31 | ... M41: =M10-M40 -> 3906349 | N41: =SUM(B41:M41) -> 19131972
A42: Net Margin % | B42: =IF(B10=0,0,B41/B10) -> 0.21863328 | C42: =IF(C10=0,0,C41/C10) -> 0.041126281 | D42: =IF(D10=0,0,D41/D10) -> 0.13451114 | E42: =IF(E10=0,0,E41/E10) -> 0.25910888 | F42: =IF(F10=0,0,F41/F10) -> 0.15627884 | G42: =IF(G10=0,0,G41/G10) -> -0.06778455 | H42: =IF(H10=0,0,H41/H10) -> 0.16090278 | I42: =IF(I10=0,0,I41/I10) -> -0.016093502 | ... N42: =IF(N10=0,0,N41/N10) -> 0.14264571
A43: Cumulative Net Profit | B43: =B41 -> 2669330.8 | C43: =B43+C41 -> 3096155.2 | D43: =C43+D41 -> 4652499.8 | E43: =D43+E41 -> 7679821 | F43: =E43+F41 -> 9509422.4 | G43: =F43+G41 -> 8918140.9 | H43: =G43+H41 -> 10884164 | I43: =H43+I41 -> 10719869 | J43: =I43+J41 -> 10831809 | ... M43: =L43+M41 -> 19131972 | N43: =M43 -> 19131972

Sheet Ratios
A1: Financial Ratios & KPIs — FY 2025
A2: All ratios computed live from the P&L Statement tab · SYNTHETIC / DUMMY DATA
A4: Ratio / Metric | B4: Jan | C4: Feb | D4: Mar | E4: Apr | F4: May | G4: Jun | H4: Jul | I4: Aug | J4: Sep | K4: Oct | L4: Nov | M4: Dec | N4: FY 2025
A5: BASE FIGURES (₺)
A6: Total Revenue | B6: ='P&L Statement'!B10 -> 12209169 | C6: ='P&L Statement'!C10 -> 10378385 | D6: ='P&L Statement'!D10 -> 11570377 | E6: ='P&L Statement'!E10 -> 11683587 | F6: ='P&L Statement'!F10 -> 11707288 | G6: ='P&L Statement'!G10 -> 8722952.9 | H6: ='P&L Statement'!H10 -> 12218699 | I6: ='P&L Statement'!I10 -> 10208736 | ... N6: ='P&L Statement'!N10 -> 1.341223e+08
A7: Total Variable Costs | B7: ='P&L Statement'!B24 -> 5881266.8 | C7: ='P&L Statement'!C24 -> 5366975.5 | D7: ='P&L Statement'!D24 -> 6821590.3 | E7: ='P&L Statement'!E24 -> 4826933.8 | F7: ='P&L Statement'!F24 -> 6191581.2 | G7: ='P&L Statement'!G24 -> 5178738.2 | H7: ='P&L Statement'!H24 -> 5947457 | I7: ='P&L Statement'!I24 -> 6285782.7 | ... N7: ='P&L Statement'!N24 -> 68424078
A8: Total Fixed Costs | B8: ='P&L Statement'!B38 -> 3658571.9 | C8: ='P&L Statement'!C38 -> 4584585.4 | D8: ='P&L Statement'!D38 -> 3192441.9 | E8: ='P&L Statement'!E38 -> 3829332.1 | F8: ='P&L Statement'!F38 -> 3686105.2 | G8: ='P&L Statement'!G38 -> 4135496 | H8: ='P&L Statement'!H38 -> 4305219.6 | I8: ='P&L Statement'!I38 -> 4087247.7 | ... N8: ='P&L Statement'!N38 -> 46566255
A9: Total Expenses | B9: ='P&L Statement'!B40 -> 9539838.7 | C9: ='P&L Statement'!C40 -> 9951560.9 | D9: ='P&L Statement'!D40 -> 10014032 | E9: ='P&L Statement'!E40 -> 8656265.9 | F9: ='P&L Statement'!F40 -> 9877686.4 | G9: ='P&L Statement'!G40 -> 9314234.3 | H9: ='P&L Statement'!H40 -> 10252677 | I9: ='P&L Statement'!I40 -> 10373030 | ... N9: ='P&L Statement'!N40 -> 1.1499033e+08
A10: Net Profit / (Loss) | B10: ='P&L Statement'!B41 -> 2669330.8 | C10: ='P&L Statement'!C41 -> 426824.39 | D10: ='P&L Statement'!D41 -> 1556344.6 | E10: ='P&L Statement'!E41 -> 3027321.2 | F10: ='P&L Statement'!F41 -> 1829601.4 | G10: ='P&L Statement'!G41 -> -591281.43 | H10: ='P&L Statement'!H41 -> 1966022.6 | I10: ='P&L Statement'!I41 -> -164294.31 | ... N10: ='P&L Statement'!N41 -> 19131972
A11: PROFITABILITY MARGINS
A12: Gross Margin % (ex-COGS) | B12: =IF('P&L Statement'!B10=0,0,('P&L Statement'!B10-'P&L Statement'!B19)/'P&L Statement'!B10) -> 0.72188167 | C12: =IF('P&L Statement'!C10=0,0,('P&L Statement'!C10-'P&L Statement'!C19)/'P&L Statement'!C10) -> 0.68136779 | D12: =IF('P&L Statement'!D10=0,0,('P&L Statement'!D10-'P&L Statement'!D19)/'P&L Statement'!D10) -> 0.70155685 | E12: =IF('P&L Statement'!E10=0,0,('P&L Statement'!E10-'P&L Statement'!E19)/'P&L Statement'!E10) -> 0.75339031 | F12: =IF('P&L Statement'!F10=0,0,('P&L Statement'!F10-'P&L Statement'!F19)/'P&L Statement'!F10) -> 0.66756052 | G12: =IF('P&L Statement'!G10=0,0,('P&L Statement'!G10-'P&L Statement'!G19)/'P&L Statement'!G10) -> 0.6499954 | H12: =IF('P&L Statement'!H10=0,0,('P&L Statement'!H10-'P&L Statement'!H19)/'P&L Statement'!H10) -> 0.66704222 | I12: =IF('P&L Statement'!I10=0,0,('P&L Statement'!I10-'P&L Statement'!I19)/'P&L Statement'!I10) -> 0.66784205 | ... N12: =IF('P&L Statement'!N10=0,0,('P&L Statement'!N10-'P&L Statement'!N19)/'P&L Statement'!N10) -> 0.6908352
A13: Contribution Margin % | B13: =IF('P&L Statement'!B10=0,0,'P&L Statement'!B26/'P&L Statement'!B10) -> 0.518291 | C13: =IF('P&L Statement'!C10=0,0,'P&L Statement'!C26/'P&L Statement'!C10) -> 0.48286989 | D13: =IF('P&L Statement'!D10=0,0,'P&L Statement'!D26/'P&L Statement'!D10) -> 0.41042626 | E13: =IF('P&L Statement'!E10=0,0,'P&L Statement'!E26/'P&L Statement'!E10) -> 0.586862 | F13: =IF('P&L Statement'!F10=0,0,'P&L Statement'!F26/'P&L Statement'!F10) -> 0.47113445 | G13: =IF('P&L Statement'!G10=0,0,'P&L Statement'!G26/'P&L Statement'!G10) -> 0.40630904 | H13: =IF('P&L Statement'!H10=0,0,'P&L Statement'!H26/'P&L Statement'!H10) -> 0.51324958 | I13: =IF('P&L Statement'!I10=0,0,'P&L Statement'!I26/'P&L Statement'!I10) -> 0.38427415 | ... N13: =IF('P&L Statement'!N10=0,0,'P&L Statement'!N26/'P&L Statement'!N10) -> 0.48983819
A14: Net Profit Margin % | B14: =IF('P&L Statement'!B10=0,0,'P&L Statement'!B41/'P&L Statement'!B10) -> 0.21863328 | C14: =IF('P&L Statement'!C10=0,0,'P&L Statement'!C41/'P&L Statement'!C10) -> 0.041126281 | D14: =IF('P&L Statement'!D10=0,0,'P&L Statement'!D41/'P&L Statement'!D10) -> 0.13451114 | E14: =IF('P&L Statement'!E10=0,0,'P&L Statement'!E41/'P&L Statement'!E10) -> 0.25910888 | F14: =IF('P&L Statement'!F10=0,0,'P&L Statement'!F41/'P&L Statement'!F10) -> 0.15627884 | G14: =IF('P&L Statement'!G10=0,0,'P&L Statement'!G41/'P&L Statement'!G10) -> -0.06778455 | H14: =IF('P&L Statement'!H10=0,0,'P&L Statement'!H41/'P&L Statement'!H10) -> 0.16090278 | I14: =IF('P&L Statement'!I10=0,0,'P&L Statement'!I41/'P&L Statement'!I10) -> -0.016093502 | ... N14: =IF('P&L Statement'!N10=0,0,'P&L Statement'!N41/'P&L Statement'!N10) -> 0.14264571
A15: COST STRUCTURE
A16: Cost Ratio (Exp / Rev) | B16: =IF('P&L Statement'!B10=0,0,'P&L Statement'!B40/'P&L Statement'!B10) -> 0.78136672 | C16: =IF('P&L Statement'!C10=0,0,'P&L Statement'!C40/'P&L Statement'!C10) -> 0.95887372 | D16: =IF('P&L Statement'!D10=0,0,'P&L Statement'!D40/'P&L Statement'!D10) -> 0.86548886 | E16: =IF('P&L Statement'!E10=0,0,'P&L Statement'!E40/'P&L Statement'!E10) -> 0.74089112 | F16: =IF('P&L Statement'!F10=0,0,'P&L Statement'!F40/'P&L Statement'!F10) -> 0.84372116 | G16: =IF('P&L Statement'!G10=0,0,'P&L Statement'!G40/'P&L Statement'!G10) -> 1.0677845 | H16: =IF('P&L Statement'!H10=0,0,'P&L Statement'!H40/'P&L Statement'!H10) -> 0.83909722 | I16: =IF('P&L Statement'!I10=0,0,'P&L Statement'!I40/'P&L Statement'!I10) -> 1.0160935 | ... N16: =IF('P&L Statement'!N10=0,0,'P&L Statement'!N40/'P&L Statement'!N10) -> 0.85735429
A17: Variable Cost Ratio | B17: =IF('P&L Statement'!B10=0,0,'P&L Statement'!B24/'P&L Statement'!B10) -> 0.481709 | C17: =IF('P&L Statement'!C10=0,0,'P&L Statement'!C24/'P&L Statement'!C10) -> 0.51713011 | D17: =IF('P&L Statement'!D10=0,0,'P&L Statement'!D24/'P&L Statement'!D10) -> 0.58957374 | E17: =IF('P&L Statement'!E10=0,0,'P&L Statement'!E24/'P&L Statement'!E10) -> 0.413138 | F17: =IF('P&L Statement'!F10=0,0,'P&L Statement'!F24/'P&L Statement'!F10) -> 0.52886555 | G17: =IF('P&L Statement'!G10=0,0,'P&L Statement'!G24/'P&L Statement'!G10) -> 0.59369096 | H17: =IF('P&L Statement'!H10=0,0,'P&L Statement'!H24/'P&L Statement'!H10) -> 0.48675042 | I17: =IF('P&L Statement'!I10=0,0,'P&L Statement'!I24/'P&L Statement'!I10) -> 0.61572585 | ... N17: =IF('P&L Statement'!N10=0,0,'P&L Statement'!N24/'P&L Statement'!N10) -> 0.51016181
A18: Fixed Cost Ratio | B18: =IF('P&L Statement'!B10=0,0,'P&L Statement'!B38/'P&L Statement'!B10) -> 0.29965772 | C18: =IF('P&L Statement'!C10=0,0,'P&L Statement'!C38/'P&L Statement'!C10) -> 0.44174361 | D18: =IF('P&L Statement'!D10=0,0,'P&L Statement'!D38/'P&L Statement'!D10) -> 0.27591512 | E18: =IF('P&L Statement'!E10=0,0,'P&L Statement'!E38/'P&L Statement'!E10) -> 0.32775312 | F18: =IF('P&L Statement'!F10=0,0,'P&L Statement'!F38/'P&L Statement'!F10) -> 0.3148556 | G18: =IF('P&L Statement'!G10=0,0,'P&L Statement'!G38/'P&L Statement'!G10) -> 0.47409359 | H18: =IF('P&L Statement'!H10=0,0,'P&L Statement'!H38/'P&L Statement'!H10) -> 0.3523468 | I18: =IF('P&L Statement'!I10=0,0,'P&L Statement'!I38/'P&L Statement'!I10) -> 0.40036765 | ... N18: =IF('P&L Statement'!N10=0,0,'P&L Statement'!N38/'P&L Statement'!N10) -> 0.34719247
A19: Variable % of Total Cost | B19: =IF('P&L Statement'!B40=0,0,'P&L Statement'!B24/'P&L Statement'!B40) -> 0.61649542 | C19: =IF('P&L Statement'!C40=0,0,'P&L Statement'!C24/'P&L Statement'!C40) -> 0.53930992 | D19: =IF('P&L Statement'!D40=0,0,'P&L Statement'!D24/'P&L Statement'!D40) -> 0.68120316 | E19: =IF('P&L Statement'!E40=0,0,'P&L Statement'!E24/'P&L Statement'!E40) -> 0.55762309 | F19: =IF('P&L Statement'!F40=0,0,'P&L Statement'!F24/'P&L Statement'!F40) -> 0.62682505 | G19: =IF('P&L Statement'!G40=0,0,'P&L Statement'!G24/'P&L Statement'!G40) -> 0.55600257 | H19: =IF('P&L Statement'!H40=0,0,'P&L Statement'!H24/'P&L Statement'!H40) -> 0.58008823 | I19: =IF('P&L Statement'!I40=0,0,'P&L Statement'!I24/'P&L Statement'!I40) -> 0.60597361 | ... N19: =IF('P&L Statement'!N40=0,0,'P&L Statement'!N24/'P&L Statement'!N40) -> 0.595042
A20: Fixed % of Total Cost | B20: =IF('P&L Statement'!B40=0,0,'P&L Statement'!B38/'P&L Statement'!B40) -> 0.38350458 | C20: =IF('P&L Statement'!C40=0,0,'P&L Statement'!C38/'P&L Statement'!C40) -> 0.46069008 | D20: =IF('P&L Statement'!D40=0,0,'P&L Statement'!D38/'P&L Statement'!D40) -> 0.31879684 | E20: =IF('P&L Statement'!E40=0,0,'P&L Statement'!E38/'P&L Statement'!E40) -> 0.44237691 | F20: =IF('P&L Statement'!F40=0,0,'P&L Statement'!F38/'P&L Statement'!F40) -> 0.37317495 | G20: =IF('P&L Statement'!G40=0,0,'P&L Statement'!G38/'P&L Statement'!G40) -> 0.44399743 | H20: =IF('P&L Statement'!H40=0,0,'P&L Statement'!H38/'P&L Statement'!H40) -> 0.41991177 | I20: =IF('P&L Statement'!I40=0,0,'P&L Statement'!I38/'P&L Statement'!I40) -> 0.39402639 | ... N20: =IF('P&L Statement'!N40=0,0,'P&L Statement'!N38/'P&L Statement'!N40) -> 0.404958
A21: GROWTH (month-over-month)
A22: Revenue MoM Growth % | B22: ="-" -> - | C22: =IF('P&L Statement'!B10=0,0,'P&L Statement'!C10/'P&L Statement'!B10-1) -> -0.14995157 | D22: =IF('P&L Statement'!C10=0,0,'P&L Statement'!D10/'P&L Statement'!C10-1) -> 0.11485327 | E22: =IF('P&L Statement'!D10=0,0,'P&L Statement'!E10/'P&L Statement'!D10-1) -> 0.0097844956 | F22: =IF('P&L Statement'!E10=0,0,'P&L Statement'!F10/'P&L Statement'!E10-1) -> 0.0020285517 | G22: =IF('P&L Statement'!F10=0,0,'P&L Statement'!G10/'P&L Statement'!F10-1) -> -0.25491258 | H22: =IF('P&L Statement'!G10=0,0,'P&L Statement'!H10/'P&L Statement'!G10-1) -> 0.40075263 | I22: =IF('P&L Statement'!H10=0,0,'P&L Statement'!I10/'P&L Statement'!H10-1) -> -0.16449895 | J22: =IF('P&L Statement'!I10=0,0,'P&L Statement'!J10/'P&L Statement'!I10-1) -> -0.058204753 | ... M22: =IF('P&L Statement'!L10=0,0,'P&L Statement'!M10/'P&L Statement'!L10-1) -> 0.24142107 | N22: ="-" -> -
A23: Net Profit MoM Growth % | B23: ="-" -> - | C23: =IF('P&L Statement'!B41=0,0,'P&L Statement'!C41/'P&L Statement'!B41-1) -> -0.8401006 | D23: =IF('P&L Statement'!C41=0,0,'P&L Statement'!D41/'P&L Statement'!C41-1) -> 2.6463346 | E23: =IF('P&L Statement'!D41=0,0,'P&L Statement'!E41/'P&L Statement'!D41-1) -> 0.94514845 | F23: =IF('P&L Statement'!E41=0,0,'P&L Statement'!F41/'P&L Statement'!E41-1) -> -0.39563684 | G23: =IF('P&L Statement'!F41=0,0,'P&L Statement'!G41/'P&L Statement'!F41-1) -> -1.323175 | H23: =IF('P&L Statement'!G41=0,0,'P&L Statement'!H41/'P&L Statement'!G41-1) -> -4.3250201 | I23: =IF('P&L Statement'!H41=0,0,'P&L Statement'!I41/'P&L Statement'!H41-1) -> -1.0835668 | J23: =IF('P&L Statement'!I41=0,0,'P&L Statement'!J41/'P&L Statement'!I41-1) -> -1.6813358 | ... M23: =IF('P&L Statement'!L41=0,0,'P&L Statement'!M41/'P&L Statement'!L41-1) -> 0.56727993 | N23: ="-" -> -
A24: BREAK-EVEN & RISK
A25: Break-even Revenue (₺) | B25: =IF('P&L Statement'!B10=0,0,'P&L Statement'!B38/IF('P&L Statement'!B10=0,1,'P&L Statement'!B26/'P&L Statement'!B10)) -> 7058914.5 | C25: =IF('P&L Statement'!C10=0,0,'P&L Statement'!C38/IF('P&L Statement'!C10=0,1,'P&L Statement'!C26/'P&L Statement'!C10)) -> 9494452.8 | D25: =IF('P&L Statement'!D10=0,0,'P&L Statement'!D38/IF('P&L Statement'!D10=0,1,'P&L Statement'!D26/'P&L Statement'!D10)) -> 7778356.8 | E25: =IF('P&L Statement'!E10=0,0,'P&L Statement'!E38/IF('P&L Statement'!E10=0,1,'P&L Statement'!E26/'P&L Statement'!E10)) -> 6525098 | F25: =IF('P&L Statement'!F10=0,0,'P&L Statement'!F38/IF('P&L Statement'!F10=0,1,'P&L Statement'!F26/'P&L Statement'!F10)) -> 7823892.3 | G25: =IF('P&L Statement'!G10=0,0,'P&L Statement'!G38/IF('P&L Statement'!G10=0,1,'P&L Statement'!G26/'P&L Statement'!G10)) -> 10178203 | H25: =IF('P&L Statement'!H10=0,0,'P&L Statement'!H38/IF('P&L Statement'!H10=0,1,'P&L Statement'!H26/'P&L Statement'!H10)) -> 8388160 | I25: =IF('P&L Statement'!I10=0,0,'P&L Statement'!I38/IF('P&L Statement'!I10=0,1,'P&L Statement'!I26/'P&L Statement'!I10)) -> 10636281 | ... N25: =IF('P&L Statement'!N10=0,0,'P&L Statement'!N38/IF('P&L Statement'!N10=0,1,'P&L Statement'!N26/'P&L Statement'!N10)) -> 95064566
A26: Margin of Safety % | B26: =IF('P&L Statement'!B26=0,0,('P&L Statement'!B41)/'P&L Statement'!B26) -> 0.421835 | C26: =IF('P&L Statement'!C26=0,0,('P&L Statement'!C41)/'P&L Statement'!C26) -> 0.085170522 | D26: =IF('P&L Statement'!D26=0,0,('P&L Statement'!D41)/'P&L Statement'!D26) -> 0.32773522 | E26: =IF('P&L Statement'!E26=0,0,('P&L Statement'!E41)/'P&L Statement'!E26) -> 0.44151586 | F26: =IF('P&L Statement'!F26=0,0,('P&L Statement'!F41)/'P&L Statement'!F26) -> 0.33170753 | G26: =IF('P&L Statement'!G26=0,0,('P&L Statement'!G41)/'P&L Statement'!G26) -> -0.16683003 | H26: =IF('P&L Statement'!H26=0,0,('P&L Statement'!H41)/'P&L Statement'!H26) -> 0.31349812 | I26: =IF('P&L Statement'!I26=0,0,('P&L Statement'!I41)/'P&L Statement'!I26) -> -0.041880261 | ... N26: =IF('P&L Statement'!N26=0,0,('P&L Statement'!N41)/'P&L Statement'!N26) -> 0.29120987
